LICENSE
MANIFEST.in
README.md
setup.py
topsis/__init__.py
topsis/__main__.py
topsis_kartik_102003565.egg-info/PKG-INFO
topsis_kartik_102003565.egg-info/SOURCES.txt
topsis_kartik_102003565.egg-info/dependency_links.txt
topsis_kartik_102003565.egg-info/entry_points.txt
topsis_kartik_102003565.egg-info/requires.txt
topsis_kartik_102003565.egg-info/top_level.txt