Metadata-Version: 2.1
Name: topsis-kartik-102003565
Version: 1.0.1
Summary: topsis
Author: Kartik Madan
Author-email: kartikmadan26@gmail.com
License: MIT
Keywords: topsis,MCDM
Classifier: License :: OSI Approved :: MIT License
Classifier: Programming Language :: Python :: 3.6
Classifier: Programming Language :: Python :: 3.7
Classifier: Programming Language :: Python :: 3.8
License-File: LICENSE
